octal/__init__.py
octal/base.py
octal/error.py
octal/instruments/__init__.py
octal/instruments/agilent8163B.py
octal/instruments/agilentDSO8000.py
octal/instruments/agilentE3640.py
octal/instruments/ametekDSP72XX.py
octal/instruments/arroyo6301.py
octal/instruments/daylightQCL.py
octal/instruments/exfoXTA50.py
octal/instruments/keithley2400.py
octal/instruments/keithley6487.py
octal/instruments/keysight86100D.py
octal/instruments/keysightE8257D.py
octal/instruments/keysightPAS.py
octal/instruments/tektronixScope.py
octal/instruments/thorlabsAPT.py
octal/instruments/thorlabsITC40XX.py
octal/instruments/thorlabsPM100.py
octal/instruments/ttiTGF3162.py
octal/sweeps/__init__.py
octal/sweeps/ac.py
octal/sweeps/dc.py
octal/sweeps/info.py
octal/sweeps/iv.py
octal/sweeps/passive.py
octal/util/__init__.py
octal/util/file_operations.py
octal/util/formatter.py
octal/util/plot.py
octal/util/util.py
octal-0.0.2.dist-info/LICENSE.txt
octal-0.0.2.dist-info/METADATA
octal-0.0.2.dist-info/WHEEL
octal-0.0.2.dist-info/top_level.txt
octal-0.0.2.dist-info/RECORD
