Metadata-Version: 2.1
Name: octal
Version: 0.0.2
Summary: Automated testing library for a wide range of instruments
Author-email: Tzu-Yun Chang <tyc1g20@soton.ac.uk>
Project-URL: Repository, https://github.com/christina-chang-tw/ORCOCTAL.git
Classifier: Programming Language :: Python :: 3
Classifier: License :: OSI Approved :: GNU General Public License v3 (GPLv3)
Classifier: Operating System :: Microsoft :: Windows
Classifier: Development Status :: 2 - Pre-Alpha
Requires-Python: >=3.6
License-File: LICENSE.txt
Requires-Dist: matplotlib
Requires-Dist: numpy
Requires-Dist: pandas
Requires-Dist: pyvisa
Requires-Dist: pyyaml
Requires-Dist: tqdm
Provides-Extra: tests
Requires-Dist: pytest ; extra == 'tests'
Requires-Dist: pywin32 ; (platform_system != "Windows") and extra == 'tests'
